qtplotlib
