Metadata-Version: 1.2
Name: qtplotlib
Version: 0.1.dev3
Summary: Plotting with Python and Qt
Home-page: http://www.jdhp.org/software_en.html#qtplotlib
Author: Jérémie DECOCK
Author-email: jd.jdhp@gmail.com
Maintainer: Jérémie DECOCK
Maintainer-email: jd.jdhp@gmail.com
License: UNKNOWN
Download-URL: http://www.jdhp.org/software_en.html#qtplotlib
Keywords: qtplotlib
Platform: UNKNOWN
Classifier: Development Status :: 4 - Beta
Classifier: Intended Audience :: Developers
Classifier: License :: OSI Approved :: MIT License
Classifier: Natural Language :: English
Classifier: Operating System :: OS Independent
Classifier: Programming Language :: Python :: 3
Classifier: Topic :: Software Development :: Libraries
Classifier: Topic :: Software Development :: Libraries :: Python Modules
Classifier: Topic :: Software Development :: Libraries :: Application Frameworks
